viiew/__init__.py
viiew-0.0.1.dist-info/LICENSE
viiew-0.0.1.dist-info/METADATA
viiew-0.0.1.dist-info/WHEEL
viiew-0.0.1.dist-info/RECORD
